gvdistpy/__init__.py
distpygv-0.2.dist-info/LICENCE.txt
distpygv-0.2.dist-info/METADATA
distpygv-0.2.dist-info/WHEEL
distpygv-0.2.dist-info/top_level.txt
distpygv-0.2.dist-info/RECORD
