Metadata-Version: 2.1
Name: distpygv
Version: 0.2
Summary: Calculation of distance with lat and long
Home-page: UNKNOWN
Author: Gaurav Gadekar
Author-email: gauravgadekar43@gmail.com
License: UNKNOWN
Platform: UNKNOWN
Classifier: Programming Language :: Python :: 3
Classifier: License :: OSI Approved :: MIT License
Classifier: Operating System :: OS Independent
